idna/__init__.py
idna/codec.py
idna/compat.py
idna/core.py
idna/idnadata.py
idna/intranges.py
idna/package_data.py
idna/uts46data.py
idna-3.0.dist-info/LICENSE.md
idna-3.0.dist-info/METADATA
idna-3.0.dist-info/WHEEL
idna-3.0.dist-info/top_level.txt
idna-3.0.dist-info/RECORD
